tmlearning/__init__.py
tmlearning/generaltmlearning.py
tmlearning/key_test.py
tmlearning/read_tminterface.py
tmlearning-1.2.0.dist-info/METADATA
tmlearning-1.2.0.dist-info/WHEEL
tmlearning-1.2.0.dist-info/licenses/LICENSE
tmlearning-1.2.0.dist-info/RECORD
