Metadata-Version: 2.4
Name: tmlearning
Version: 1.2.0
Summary: A Python library to create and use machine learning TrackMania AIs.
Project-URL: Homepage, https://github.com/att131/tmlearning
Project-URL: Bug Tracker, https://github.com/att131/tmlearning/issues
Project-URL: Source, https://github.com/att131/tmlearning
Project-URL: Documentation, https://github.com/att131/tmlearning#readme
Author-email: Atticus Alarcon <atticusaalarcon@gmail.com>
License: Copyright 2025 Atticus Alarcon
License-File: LICENSE
Keywords: ai,bot,tmlearning,trackmania
Classifier: License :: OSI Approved :: MIT License
Classifier: Operating System :: OS Independent
Classifier: Programming Language :: Python :: 3
Requires-Python: >=3.12
Requires-Dist: keyboard>=0.13.5
Requires-Dist: mss>=10.0.0
Requires-Dist: numpy>=1.26.4
Requires-Dist: pillow>=11.2.1
Requires-Dist: pynput>=1.8.1
Requires-Dist: torch==2.8.0.dev20250504+cu128
